setpwef-0.1.6.dist-info/METADATA
setpwef-0.1.6.dist-info/WHEEL
setpwef-0.1.6.dist-info/license_files/LICENSE
setpwef/__init__.py
setpwef/setpwef.cpython-312-darwin.so
setpwef-0.1.6.dist-info/RECORD
