Metadata-Version: 2.1
Name: setpwef
Version: 0.1.6
Classifier: Programming Language :: Rust
Classifier: Programming Language :: Python :: Implementation :: CPython
Classifier: Programming Language :: Python :: Implementation :: PyPy
License-File: LICENSE
Summary: set password excel file in python
Author: Jess <dev.bearabbit@gmail.com>
Author-email: Jess <dev.bearabbit@gmail.com>
License: MIT
Requires-Python: >=3.7
Project-URL: Source Code, https://github.com/Hyeonji-Ryu/setpwef
